glmnetforpython/GLMnet.so
glmnetforpython/__init__.py
glmnetforpython/coxnet.py
glmnetforpython/cvcompute.py
glmnetforpython/cvelnet.py
glmnetforpython/cvfishnet.py
glmnetforpython/cvglmnet.py
glmnetforpython/cvglmnetCoef.py
glmnetforpython/cvglmnetPlot.py
glmnetforpython/cvglmnetPredict.py
glmnetforpython/cvlognet.py
glmnetforpython/cvmrelnet.py
glmnetforpython/cvmultnet.py
glmnetforpython/dataprocess.py
glmnetforpython/elnet.py
glmnetforpython/fishnet.py
glmnetforpython/glmnet.py
glmnetforpython/glmnetCoef.py
glmnetforpython/glmnetControl.py
glmnetforpython/glmnetPlot.py
glmnetforpython/glmnetPredict.py
glmnetforpython/glmnetPrint.py
glmnetforpython/glmnetSet.py
glmnetforpython/glmnet_class.py
glmnetforpython/loadGlmLib.py
glmnetforpython/lognet.py
glmnetforpython/mrelnet.py
glmnetforpython/printDict.py
glmnetforpython/structtype.py
glmnetforpython/wtmean.py
glmnetforpython-0.3.3.dist-info/LICENSE
glmnetforpython-0.3.3.dist-info/METADATA
glmnetforpython-0.3.3.dist-info/WHEEL
glmnetforpython-0.3.3.dist-info/top_level.txt
glmnetforpython-0.3.3.dist-info/RECORD
